MANIFEST.in
README.rst
litekv.py
setup.py
litekv.egg-info/PKG-INFO
litekv.egg-info/SOURCES.txt
litekv.egg-info/dependency_links.txt
litekv.egg-info/top_level.txt