Metadata-Version: 1.0
Name: litekv
Version: 0.6
Summary: Simple kv store for Python
Home-page: http://github.com/reorx/litekv
Author: reorx
Author-email: UNKNOWN
License: UNKNOWN
Platform: UNKNOWN
